discohook/__init__.py
discohook/__main__.py
discohook/client.py
Discohook-1.0.0.dist-info/LICENSE
Discohook-1.0.0.dist-info/METADATA
Discohook-1.0.0.dist-info/WHEEL
Discohook-1.0.0.dist-info/entry_points.txt
Discohook-1.0.0.dist-info/top_level.txt
Discohook-1.0.0.dist-info/RECORD
