Metadata-Version: 2.1
Name: Discohook
Version: 1.0.0
Summary: A basic Library to send Discord Webhook
Home-page: https://github.com/Janakthegamer/Discohook
Author: JanakXD
Author-email: janak@panarastudios.in
License: MIT License
Project-URL: Bug Tracker, https://github.com/Janakthegamer/Discohook/issues
Platform: UNKNOWN
Classifier: Environment :: Web Environment
Classifier: Intended Audience :: Developers
Classifier: License :: OSI Approved :: MIT License
Classifier: Operating System :: OS Independent
Classifier: Programming Language :: Python
Classifier: Programming Language :: Python :: 3.6
Classifier: Programming Language :: Python :: 3.7
Classifier: Programming Language :: Python :: 3.8
Classifier: Topic :: Internet :: WWW/HTTP
Classifier: Topic :: Internet :: WWW/HTTP :: Dynamic Content
License-File: LICENSE
Requires-Dist: requests (>=2.19.1)
